runif/__init__.py
runif-0.0.3.dist-info/LICENSE
runif-0.0.3.dist-info/METADATA
runif-0.0.3.dist-info/WHEEL
runif-0.0.3.dist-info/top_level.txt
runif-0.0.3.dist-info/RECORD
