Metadata-Version: 2.1
Name: runif
Version: 0.0.3
Summary: Idempotent and minimal python library for rapid scripting.
Home-page: https://gioorgi.com/2020/runif/
Author: Giovanni Giorgi
Author-email: jj@gioorgi.com
Maintainer: Giovanni Giorgi
Maintainer-email: jj@gioorgi.com
License: BSD-3-Clause
Project-URL: Documentation, https://runif.readthedocs.io/
Project-URL: Code, https://github.com/daitangio/runif
Project-URL: Issue tracker, https://github.com/daitangio/runif/issues
Platform: UNKNOWN
Classifier: Development Status :: 5 - Production/Stable
Classifier: Intended Audience :: Developers
Classifier: License :: OSI Approved :: BSD License
Classifier: Operating System :: OS Independent
Classifier: Programming Language :: Python
Classifier: Programming Language :: Python :: 3
Classifier: Programming Language :: Python :: 3.6
Classifier: Programming Language :: Python :: 3.7
Requires-Python: >=3.6
